leap.soledad.client-0.9.6.post2-py2.7-nspkg.pth
leap/soledad/client/__init__.py
leap/soledad/client/_crypto.py
leap/soledad/client/_document.py
leap/soledad/client/_http.py
leap/soledad/client/_pipes.py
leap/soledad/client/_recovery_code.py
leap/soledad/client/_version.py
leap/soledad/client/api.py
leap/soledad/client/auth.py
leap/soledad/client/crypto.py
leap/soledad/client/events.py
leap/soledad/client/interfaces.py
leap/soledad/client/shared_db.py
leap/soledad/client/sync.py
leap/soledad/client/_db/__init__.py
leap/soledad/client/_db/adbapi.py
leap/soledad/client/_db/blobs.py
leap/soledad/client/_db/dbschema.sql
leap/soledad/client/_db/pragmas.py
leap/soledad/client/_db/sqlcipher.py
leap/soledad/client/_db/sqlite.py
leap/soledad/client/_secrets/__init__.py
leap/soledad/client/_secrets/crypto.py
leap/soledad/client/_secrets/storage.py
leap/soledad/client/_secrets/util.py
leap/soledad/client/http_target/__init__.py
leap/soledad/client/http_target/api.py
leap/soledad/client/http_target/fetch.py
leap/soledad/client/http_target/fetch_protocol.py
leap/soledad/client/http_target/send.py
leap/soledad/client/http_target/send_protocol.py
leap/soledad/client/http_target/support.py
leap.soledad.client-0.9.6.post2.dist-info/DESCRIPTION.rst
leap.soledad.client-0.9.6.post2.dist-info/METADATA
leap.soledad.client-0.9.6.post2.dist-info/RECORD
leap.soledad.client-0.9.6.post2.dist-info/WHEEL
leap.soledad.client-0.9.6.post2.dist-info/metadata.json
leap.soledad.client-0.9.6.post2.dist-info/namespace_packages.txt
leap.soledad.client-0.9.6.post2.dist-info/pbr.json
leap.soledad.client-0.9.6.post2.dist-info/top_level.txt
