Metadata-Version: 2.0
Name: leap.soledad.client
Version: 0.9.6.post2
Summary: Synchronization of locally encrypted data among devices (client components).
Home-page: https://leap.se/
Author: Kali Kaneko
Author-email: kali@leap.se
License: GPLv3+
Download-URL: https://github.com/leapcode/bitmask_client/archive/0.9.6.tar.gz
Platform: UNKNOWN
Classifier: Development Status :: 3 - Alpha
Classifier: Intended Audience :: Developers
Classifier: License :: OSI Approved :: GNU General Public License v3 or later (GPLv3+)
Classifier: Environment :: Console
Classifier: Operating System :: OS Independent
Classifier: Operating System :: POSIX
Classifier: Programming Language :: Python :: 2.7
Classifier: Topic :: Database :: Front-Ends
Classifier: Topic :: Software Development :: Libraries :: Python Modules
Requires-Dist: cryptography
Requires-Dist: leap.common
Requires-Dist: leap.soledad.common
Requires-Dist: pysqlcipher
Requires-Dist: scrypt
Requires-Dist: treq
Requires-Dist: twisted
Requires-Dist: zope.proxy
Provides-Extra: signaling
Requires-Dist: leap.common (>=0.3.0); extra == 'signaling'
